spotify_lyrics_scraper/__init__.py
spotify_lyrics_scraper-1.2.2.dist-info/METADATA
spotify_lyrics_scraper-1.2.2.dist-info/WHEEL
spotify_lyrics_scraper-1.2.2.dist-info/licenses/LICENSE
spotify_lyrics_scraper-1.2.2.dist-info/RECORD
