Metadata-Version: 2.1
Name: spotify_lyrics_scraper
Version: 1.2.2
Summary: This allows you to grab Spotify lyrics from their API. You can input song names or track IDs. Supports proxies.
Project-URL: GitHub, https://github.com/PolyAnthi/spotify-lyrics-scraper
Author-email: PolyAnthi <polyanthi_pumicing@aleeas.com>
License-File: LICENSE
Classifier: License :: OSI Approved :: MIT License
Classifier: Operating System :: OS Independent
Classifier: Programming Language :: Python :: 3
Requires-Python: >=3.7
